claim_sampling/__init__.py
claim_sampling/admin.py
claim_sampling/apps.py
claim_sampling/gql_mutations.py
claim_sampling/gql_queries.py
claim_sampling/models.py
claim_sampling/schema.py
claim_sampling/services.py
claim_sampling/signals.py
claim_sampling/tests.py
claim_sampling/urls.py
claim_sampling/views.py
claim_sampling/migrations/0001_initial.py
claim_sampling/migrations/0002_remove_claimsamplingbatchassignment_claim_batch_id_and_more.py
claim_sampling/migrations/0003_initial.py
claim_sampling/migrations/0004_rename_claim_id_claimsamplingbatchassignment_claim_and_more.py
claim_sampling/migrations/0005_alter_claimsamplingbatchassignment_status_and_more.py
claim_sampling/migrations/0006_alter_claimsamplingbatchassignment_claim_and_more.py
claim_sampling/migrations/__init__.py
openimis_be_claim_sampling-1.2.0.dist-info/licenses/LICENSE.md
openimis_be_claim_sampling-1.2.0.dist-info/METADATA
openimis_be_claim_sampling-1.2.0.dist-info/WHEEL
openimis_be_claim_sampling-1.2.0.dist-info/top_level.txt
openimis_be_claim_sampling-1.2.0.dist-info/RECORD
